[
  {
    "date": "2022-10-07",
    "average": 1.9948119325551232,
    "total_negative": 0,
    "total_neutral": 4,
    "total_positive": 767
  },
  {
    "date": "2022-10-08",
    "average": 1.0596833130328869,
    "total_negative": 6,
    "total_neutral": 760,
    "total_positive": 55
  },
  {
    "date": "2022-10-09",
    "average": 1.4266517357222843,
    "total_negative": 101,
    "total_neutral": 310,
    "total_positive": 482
  },
  {
    "date": "2022-10-10",
    "average": 1.4266517357222843,
    "total_negative": 101,
    "total_neutral": 310,
    "total_positive": 482
  },
  {
    "date": "2022-10-11",
    "average": 0.0671981776765375,
    "total_negative": 819,
    "total_neutral": 59,
    "total_positive": 0
  },
  {
    "date": "2022-10-12",
    "average": 1.010204081632653,
    "total_negative": 5,
    "total_neutral": 863,
    "total_positive": 14
  },
  {
    "date": "2022-10-13",
    "average": 0.4900816802800466,
    "total_negative": 601,
    "total_neutral": 92,
    "total_positive": 164
  },
  {
    "date": "2022-10-14",
    "average": 1.5702479338842976,
    "total_negative": 111,
    "total_neutral": 142,
    "total_positive": 594
  },
  {
    "date": "2022-10-15",
    "average": 0.7627906976744186,
    "total_negative": 207,
    "total_neutral": 650,
    "total_positive": 3
  },
  {
    "date": "2022-10-16",
    "average": 1.6518691588785046,
    "total_negative": 1,
    "total_neutral": 296,
    "total_positive": 559
  },
  {
    "date": "2022-10-17",
    "average": 0.0472813238770685,
    "total_negative": 811,
    "total_neutral": 30,
    "total_positive": 5
  },
  {
    "date": "2022-10-18",
    "average": 0.0326876513317191,
    "total_negative": 800,
    "total_neutral": 25,
    "total_positive": 1
  },
  {
    "date": "2022-10-19",
    "average": 0.0539609644087256,
    "total_negative": 831,
    "total_neutral": 33,
    "total_positive": 7
  },
  {
    "date": "2022-10-20",
    "average": 1.0193548387096774,
    "total_negative": 0,
    "total_neutral": 304,
    "total_positive": 6
  },
  {
    "date": "2022-10-21",
    "average": 0.0654205607476635,
    "total_negative": 828,
    "total_neutral": 0,
    "total_positive": 28
  },
  {
    "date": "2022-10-22",
    "average": 0.0573099415204678,
    "total_negative": 807,
    "total_neutral": 47,
    "total_positive": 1
  },
  {
    "date": "2022-10-23",
    "average": 0.0459242250287026,
    "total_negative": 833,
    "total_neutral": 36,
    "total_positive": 2
  },
  {
    "date": "2022-10-24",
    "average": 0.0707434052757793,
    "total_negative": 795,
    "total_neutral": 19,
    "total_positive": 20
  },
  {
    "date": "2022-10-25",
    "average": 1.7365853658536583,
    "total_negative": 78,
    "total_neutral": 60,
    "total_positive": 682
  },
  {
    "date": "2022-10-26",
    "average": 0.0967032967032967,
    "total_negative": 851,
    "total_neutral": 30,
    "total_positive": 29
  },
  {
    "date": "2022-10-27",
    "average": 1.976109215017065,
    "total_negative": 10,
    "total_neutral": 1,
    "total_positive": 868
  },
  {
    "date": "2022-10-28",
    "average": 1.9709639953542395,
    "total_negative": 2,
    "total_neutral": 21,
    "total_positive": 838
  },
  {
    "date": "2022-10-29",
    "average": 0.8434982738780207,
    "total_negative": 464,
    "total_neutral": 77,
    "total_positive": 328
  },
  {
    "date": "2022-10-30",
    "average": 1.3010882708585247,
    "total_negative": 1,
    "total_neutral": 576,
    "total_positive": 250
  },
  {
    "date": "2022-10-31",
    "average": 1.6,
    "total_negative": 40,
    "total_neutral": 250,
    "total_positive": 535
  },
  {
    "date": "2022-11-01",
    "average": 1.6,
    "total_negative": 40,
    "total_neutral": 250,
    "total_positive": 535
  },
  {
    "date": "2022-11-02",
    "average": 1.984431137724551,
    "total_negative": 2,
    "total_neutral": 9,
    "total_positive": 824
  },
  {
    "date": "2022-11-03",
    "average": 1.128654970760234,
    "total_negative": 334,
    "total_neutral": 77,
    "total_positive": 444
  },
  {
    "date": "2022-11-04",
    "average": 1.0105633802816902,
    "total_negative": 0,
    "total_neutral": 843,
    "total_positive": 9
  },
  {
    "date": "2022-11-05",
    "average": 0.7962085308056872,
    "total_negative": 507,
    "total_neutral": 2,
    "total_positive": 335
  },
  {
    "date": "2022-11-06",
    "average": 0.4145785876993166,
    "total_negative": 641,
    "total_neutral": 110,
    "total_positive": 127
  },
  {
    "date": "2022-11-07",
    "average": 0.1330376940133037,
    "total_negative": 790,
    "total_neutral": 104,
    "total_positive": 8
  },
  {
    "date": "2022-11-08",
    "average": 1.0011273957158964,
    "total_negative": 0,
    "total_neutral": 886,
    "total_positive": 1
  },
  {
    "date": "2022-11-09",
    "average": 0.9786729857819904,
    "total_negative": 18,
    "total_neutral": 826,
    "total_positive": 0
  },
  {
    "date": "2022-11-10",
    "average": 1.0540865384615383,
    "total_negative": 280,
    "total_neutral": 227,
    "total_positive": 325
  },
  {
    "date": "2022-11-11",
    "average": 1.886838868388684,
    "total_negative": 38,
    "total_neutral": 16,
    "total_positive": 759
  },
  {
    "date": "2022-11-12",
    "average": 1.9773936170212767,
    "total_negative": 0,
    "total_neutral": 17,
    "total_positive": 735
  },
  {
    "date": "2022-11-13",
    "average": 1.4246947082767978,
    "total_negative": 147,
    "total_neutral": 130,
    "total_positive": 460
  },
  {
    "date": "2022-11-14",
    "average": 1.532967032967033,
    "total_negative": 4,
    "total_neutral": 332,
    "total_positive": 392
  },
  {
    "date": "2022-11-15",
    "average": 1.3601895734597156,
    "total_negative": 1,
    "total_neutral": 403,
    "total_positive": 229
  },
  {
    "date": "2022-11-16",
    "average": 0,
    "total_negative": 0,
    "total_neutral": 0,
    "total_positive": 0
  },
  {
    "date": "2022-11-17",
    "average": 1.4912985274431056,
    "total_negative": 189,
    "total_neutral": 2,
    "total_positive": 556
  },
  {
    "date": "2022-11-18",
    "average": 0.8074454428754814,
    "total_negative": 324,
    "total_neutral": 281,
    "total_positive": 174
  },
  {
    "date": "2022-11-19",
    "average": 0.1591478696741854,
    "total_negative": 728,
    "total_neutral": 13,
    "total_positive": 57
  },
  {
    "date": "2022-11-20",
    "average": 0.090566037735849,
    "total_negative": 243,
    "total_neutral": 20,
    "total_positive": 2
  },
  {
    "date": "2022-11-21",
    "average": 0.0228571428571428,
    "total_negative": 171,
    "total_neutral": 4,
    "total_positive": 0
  },
  {
    "date": "2022-11-22",
    "average": 1.424390243902439,
    "total_negative": 4,
    "total_neutral": 464,
    "total_positive": 352
  },
  {
    "date": "2022-11-23",
    "average": 1.7203791469194314,
    "total_negative": 75,
    "total_neutral": 86,
    "total_positive": 683
  },
  {
    "date": "2022-11-24",
    "average": 0.9975757575757576,
    "total_negative": 121,
    "total_neutral": 585,
    "total_positive": 119
  },
  {
    "date": "2022-11-25",
    "average": 1.040909090909091,
    "total_negative": 7,
    "total_neutral": 619,
    "total_positive": 34
  },
  {
    "date": "2022-11-26",
    "average": 0.9698795180722892,
    "total_negative": 283,
    "total_neutral": 289,
    "total_positive": 258
  },
  {
    "date": "2022-11-27",
    "average": 0.7579462102689487,
    "total_negative": 508,
    "total_neutral": 0,
    "total_positive": 310
  },
  {
    "date": "2022-11-28",
    "average": 1.7037037037037035,
    "total_negative": 11,
    "total_neutral": 226,
    "total_positive": 600
  },
  {
    "date": "2022-11-29",
    "average": 1.862227324913892,
    "total_negative": 1,
    "total_neutral": 118,
    "total_positive": 752
  },
  {
    "date": "2022-11-30",
    "average": 0.4643734643734644,
    "total_negative": 437,
    "total_neutral": 376,
    "total_positive": 1
  },
  {
    "date": "2022-12-01",
    "average": "",
    "total_negative": "",
    "total_neutral": "",
    "total_positive": ""
  },
  {
    "date": "2022-12-02",
    "average": "",
    "total_negative": "",
    "total_neutral": "",
    "total_positive": ""
  },
  {
    "date": "2022-12-03",
    "average": "",
    "total_negative": "",
    "total_neutral": "",
    "total_positive": ""
  },
  {
    "date": "2022-12-04",
    "average": "",
    "total_negative": "",
    "total_neutral": "",
    "total_positive": ""
  },
  {
    "date": "2022-12-05",
    "average": "",
    "total_negative": "",
    "total_neutral": "",
    "total_positive": ""
  },
  {
    "date": "2022-12-06",
    "average": "",
    "total_negative": "",
    "total_neutral": "",
    "total_positive": ""
  },
  {
    "date": "2022-12-07",
    "average": "",
    "total_negative": "",
    "total_neutral": "",
    "total_positive": ""
  },
  {
    "date": "2022-12-08",
    "average": "",
    "total_negative": "",
    "total_neutral": "",
    "total_positive": ""
  },
  {
    "date": "2022-12-09",
    "average": "",
    "total_negative": "",
    "total_neutral": "",
    "total_positive": ""
  },
  {
    "date": "2022-12-10",
    "average": "",
    "total_negative": "",
    "total_neutral": "",
    "total_positive": ""
  },
  {
    "date": "2022-12-11",
    "average": "",
    "total_negative": "",
    "total_neutral": "",
    "total_positive": ""
  },
  {
    "date": "2022-12-12",
    "average": "",
    "total_negative": "",
    "total_neutral": "",
    "total_positive": ""
  },
  {
    "date": "2022-12-13",
    "average": "",
    "total_negative": "",
    "total_neutral": "",
    "total_positive": ""
  },
  {
    "date": "2022-12-14",
    "average": "",
    "total_negative": "",
    "total_neutral": "",
    "total_positive": ""
  },
  {
    "date": "2022-12-15",
    "average": "",
    "total_negative": "",
    "total_neutral": "",
    "total_positive": ""
  },
  {
    "date": "2022-12-16",
    "average": "",
    "total_negative": "",
    "total_neutral": "",
    "total_positive": ""
  },
  {
    "date": "2022-12-17",
    "average": "",
    "total_negative": "",
    "total_neutral": "",
    "total_positive": ""
  },
  {
    "date": "2022-12-18",
    "average": "",
    "total_negative": "",
    "total_neutral": "",
    "total_positive": ""
  },
  {
    "date": "2022-12-19",
    "average": "",
    "total_negative": "",
    "total_neutral": "",
    "total_positive": ""
  },
  {
    "date": "2022-12-20",
    "average": "",
    "total_negative": "",
    "total_neutral": "",
    "total_positive": ""
  },
  {
    "date": "2022-12-21",
    "average": "",
    "total_negative": "",
    "total_neutral": "",
    "total_positive": ""
  },
  {
    "date": "2022-12-22",
    "average": "",
    "total_negative": "",
    "total_neutral": "",
    "total_positive": ""
  },
  {
    "date": "2022-12-23",
    "average": "",
    "total_negative": "",
    "total_neutral": "",
    "total_positive": ""
  },
  {
    "date": "2022-12-24",
    "average": "",
    "total_negative": "",
    "total_neutral": "",
    "total_positive": ""
  },
  {
    "date": "2022-12-25",
    "average": "",
    "total_negative": "",
    "total_neutral": "",
    "total_positive": ""
  },
  {
    "date": "2022-12-26",
    "average": "",
    "total_negative": "",
    "total_neutral": "",
    "total_positive": ""
  },
  {
    "date": "2022-12-27",
    "average": "",
    "total_negative": "",
    "total_neutral": "",
    "total_positive": ""
  },
  {
    "date": "2022-12-28",
    "average": "",
    "total_negative": "",
    "total_neutral": "",
    "total_positive": ""
  },
  {
    "date": "2022-12-29",
    "average": "",
    "total_negative": "",
    "total_neutral": "",
    "total_positive": ""
  },
  {
    "date": "2022-12-30",
    "average": "",
    "total_negative": "",
    "total_neutral": "",
    "total_positive": ""
  },
  {
    "date": "2022-12-31",
    "average": "",
    "total_negative": "",
    "total_neutral": "",
    "total_positive": ""
  }
]